byted_overpass_toutiao_live_talk_gotalk/__init__.py
byted_overpass_toutiao_live_talk_gotalk-0.0.1.dist-info/METADATA
byted_overpass_toutiao_live_talk_gotalk-0.0.1.dist-info/WHEEL
byted_overpass_toutiao_live_talk_gotalk-0.0.1.dist-info/top_level.txt
byted_overpass_toutiao_live_talk_gotalk-0.0.1.dist-info/RECORD
